setup.py
pyperry/__init__.py
pyperry/association.py
pyperry/base.py
pyperry/caching.py
pyperry/callbacks.py
pyperry/errors.py
pyperry/field.py
pyperry/relation.py
pyperry/response.py
pyperry/response_parsers.py
pyperry/scope.py
pyperry.egg-info/PKG-INFO
pyperry.egg-info/SOURCES.txt
pyperry.egg-info/dependency_links.txt
pyperry.egg-info/requires.txt
pyperry.egg-info/top_level.txt
pyperry/adapter/__init__.py
pyperry/adapter/abstract_adapter.py
pyperry/adapter/bertrpc_adapter.py
pyperry/adapter/http.py
pyperry/middlewares/__init__.py
pyperry/middlewares/local_cache.py
pyperry/middlewares/model_bridge.py
pyperry/processors/__init__.py
pyperry/processors/preload_associations.py
tests/fixtures/__init__.py
tests/fixtures/association_models.py
tests/fixtures/doc_models.py
tests/fixtures/extended_association_models.py
tests/fixtures/test_adapter.py
tests/helpers/__init__.py
tests/helpers/http_test_server.py