Metadata-Version: 1.0
Name: pyperry
Version: 1.2.10
Summary: Python library for querying and mapping data through generic interfaces (this is a port of the Ruby "perry" library)
Home-page: http://github.com/tpett/pyperry
Author: Travis Petticrew
Author-email: travis@petticrew.net
License: MIT
Download-URL: http://pypi.python.org/packages/source/p/pyperry/pyperry-1.2.10.tar.gz
Platform: UNKNOWN
Classifier: Development Status :: 4 - Beta
Classifier: Environment :: Console
Classifier: Intended Audience :: Developers
Classifier: License :: OSI Approved :: MIT License
Classifier: Operating System :: OS Independent
Classifier: Programming Language :: Python
